Homework1/hw2_div.v
module div(
    input [3:0] din,
    output [2:0] dout
);
    reg [2:0] mid;
    always @(din) begin
        mid=3'b000;
        if(din<=4'b1111)
            mid=3'b101;
        if(din<=4'b1100)
            mid=3'b100;
        if(din<=4'b1001)
            mid=3'b011;
        if(din<=4'b0110)
            mid=3'b010;
        if(din<=4'b0011)
            mid=3'b001;
        if(din<=4'b0000)
            mid=3'b000;        
    end
    assign dout=mid;
endmodule

Homework1/hw2_test.v
`timescale 1ns/1ps
module test ;
    reg [3:0] din;
    wire [2:0] dout;
    div div1(din,dout);

    initial begin
        din=0;
        #10 din=$random;
        #10 din=$random;
        #10 din=$random;
        #10 din=$random;
        #10 din=$random;
        #10 din=$random;
        #10 din=$random;
        #10 din=$random;
        #10 din=$random;
        #10 din=$random;
        #10 din=$random;
        #10 din=$random;
        #10 din=$random;
        #10 din=$random;
        #10 din=$random;
        $finish();
    end
    initial begin
        $dumpfile("hw2_test.vcd");
        $dumpvars(0);
    end
endmodule

Homework1/hw2_test.vcd
$date
	Sun Oct 29 20:20:39 2023
$end
$version
	Icarus Verilog
$end
$timescale
	1ps
$end
$scope module test $end
$var wire 3 ! dout [2:0] $end
$var reg 4 " din [3:0] $end
$scope module div1 $end
$var wire 4 # din [3:0] $end
$var wire 3 $ dout [2:0] $end
$var reg 3 % mid [2:0] $end
$upscope $end
$upscope $end
$enddefinitions $end
#0
$dumpvars
b0 %
b0 $
b0 #
b0 "
b0 !
$end
#10000
b10 !
b10 $
b10 %
b100 "
b100 #
#20000
b1 !
b1 $
b1 %
b1 "
b1 #
#30000
b11 !
b11 $
b11 %
b1001 "
b1001 #
#40000
b1 !
b1 $
b1 %
b11 "
b11 #
#50000
b101 !
b101 $
b101 %
b1101 "
b1101 #
#70000
b10 !
b10 $
b10 %
b101 "
b101 #
#80000
b1 !
b1 $
b1 %
b10 "
b10 #
#90000
b1 !
b1 $
b1 %
b1 "
b1 #
#100000
b101 !
b101 $
b101 %
b1101 "
b1101 #
#110000
b10 !
b10 $
b10 %
b110 "
b110 #
#120000
b101 !
b101 $
b101 %
b1101 "
b1101 #
#140000
b100 !
b100 $
b100 %
b1100 "
b1100 #
#150000
b11 !
b11 $
b11 %
b1001 "
b1001 #
